allauth_keycloak_ext/__init__.py
allauth_keycloak_ext/provider.py
allauth_keycloak_ext/tests.py
allauth_keycloak_ext/urls.py
allauth_keycloak_ext/views.py
django_allauth_keycloak_ext-0.1.2.dist-info/LICENSE.txt
django_allauth_keycloak_ext-0.1.2.dist-info/METADATA
django_allauth_keycloak_ext-0.1.2.dist-info/WHEEL
django_allauth_keycloak_ext-0.1.2.dist-info/top_level.txt
django_allauth_keycloak_ext-0.1.2.dist-info/RECORD
