Metadata-Version: 2.1
Name: django-allauth-keycloak-ext
Version: 0.1.2
Summary: Extensions for django-allauth module to support groups of Keycloak.
Home-page: https://github.com/wonderu/allauth-keycloak-ext/
Author: Igor Podsekin
Author-email: py@wonderu.com
Project-URL: Changelog, https://github.com/wonderu/allauth-keycloak-ext/blob/master/ChangeLog.rst
Project-URL: Source, https://github.com/wonderu/allauth-keycloak-ext/
Project-URL: Tracker, https://github.com/wonderu/allauth-keycloak-ext/issues
Project-URL: Donate, https://github.com/sponsors/wonderu
Keywords: django auth account social openid twitter facebook oauth registration
Classifier: Development Status :: 4 - Beta
Classifier: Intended Audience :: Developers
Classifier: Topic :: Software Development :: Libraries :: Python Modules
Classifier: License :: OSI Approved :: MIT License
Classifier: Programming Language :: Python :: 3
Classifier: Programming Language :: Python :: 3.8
Classifier: Programming Language :: Python :: 3.9
Classifier: Programming Language :: Python :: 3.10
Classifier: Programming Language :: Python :: 3.11
Classifier: Programming Language :: Python :: 3 :: Only
Classifier: Environment :: Web Environment
Classifier: Topic :: Internet
Classifier: Operating System :: OS Independent
Classifier: Framework :: Django :: 4.0
Classifier: Framework :: Django :: 4.1
Requires-Python: >=3.8
License-File: LICENSE.txt
Requires-Dist: django-allauth (>=0.52.0)
